_reaktome.cpython-312-x86_64-linux-gnu.so
reaktome/__init__.py
reaktome/__version__.py
reaktome-0.1.7.dist-info/METADATA
reaktome-0.1.7.dist-info/WHEEL
reaktome-0.1.7.dist-info/top_level.txt
reaktome-0.1.7.dist-info/RECORD
reaktome-0.1.7.dist-info/licenses/LICENSE
