Metadata-Version: 2.4
Name: reaktome
Version: 0.1.7
Summary: Advisory-only setattr hooks with veto support
Requires-Python: >=3.12
License-File: LICENSE
Dynamic: license-file
Dynamic: requires-python
